[
    {
      "name": "Ana Rodríguez",
      "fecha_nacimiento": "1985-10-20",
      "telefono": "555-123-4567",
      "correo_electronico": "ana@example.com",
      "direccion": "Avenida Ficticia 456",
      "contraseña": "AnaPass123"
    },
    {
      "name": "Luis Martínez",
      "fecha_nacimiento": "1992-03-08",
      "telefono": "777-987-6543",
      "correo_electronico": "luis@example.com",
      "direccion": "Calle Ficticia 789",
      "contraseña": "LuisPass456"
    },
    {
      "name": "María Gómez",
      "fecha_nacimiento": "1988-12-15",
      "telefono": "333-555-8888",
      "correo_electronico": "maria@example.com",
      "direccion": "Plaza Ficticia 101",
      "contraseña": "MariaPass789"
    },
    {
      "name": "Carlos Sánchez",
      "fecha_nacimiento": "1977-06-25",
      "telefono": "444-222-1111",
      "correo_electronico": "carlos@example.com",
      "direccion": "Carrera Ficticia 555",
      "contraseña": "CarlosPass555"
    },
    {
      "name": "Isabel López",
      "fecha_nacimiento": "1998-08-02",
      "telefono": "666-777-9999",
      "correo_electronico": "isabel@example.com",
      "direccion": "Callejón Ficticio 222",
      "contraseña": "IsabelPass222"
    },
    {
      "name": "Manuel García",
      "fecha_nacimiento": "1991-01-12",
      "telefono": "888-555-4444",
      "correo_electronico": "manuel@example.com",
      "direccion": "Avenida Ficticia 789",
      "contraseña": "ManuelPass789"
    },
    {
      "name": "Laura Fernández",
      "fecha_nacimiento": "1995-07-30",
      "telefono": "999-333-2222",
      "correo_electronico": "laura@example.com",
      "direccion": "Calle Ficticia 567",
      "contraseña": "LauraPass567"
    },
    {
      "name": "Pedro Ramírez",
      "fecha_nacimiento": "1982-11-05",
      "telefono": "111-222-3333",
      "correo_electronico": "pedro@example.com",
      "direccion": "Avenida Ficticia 123",
      "contraseña": "PedroPass123"
    },
    {
      "name": "Sofía Morales",
      "fecha_nacimiento": "1993-09-18",
      "telefono": "222-444-5555",
      "correo_electronico": "sofia@example.com",
      "direccion": "Plaza Ficticia 456",
      "contraseña": "SofiaPass456"
    },
    {
      "name": "Eduardo López",
      "fecha_nacimiento": "1987-04-09",
      "telefono": "333-111-6666",
      "correo_electronico": "eduardo@example.com",
      "direccion": "Calle Ficticia 789",
      "contraseña": "EduardoPass789"
    },
    {
      "name": "Carolina Martín",
      "fecha_nacimiento": "1990-06-21",
      "telefono": "444-666-7777",
      "correo_electronico": "carolina@example.com",
      "direccion": "Avenida Ficticia 101",
      "contraseña": "CarolinaPass101"
    },
    {
      "name": "Andrés Pérez",
      "fecha_nacimiento": "1984-03-28",
      "telefono": "555-888-9999",
      "correo_electronico": "andres@example.com",
      "direccion": "Calle Ficticia 222",
      "contraseña": "AndresPass222"
    },
    {
      "name": "Valentina Ruiz",
      "fecha_nacimiento": "1997-02-14",
      "telefono": "666-222-3333",
      "correo_electronico": "valentina@example.com",
      "direccion": "Plaza Ficticia 333",
      "contraseña": "ValentinaPass333"
    }
  ]